suvifilemod04/__init__.py
suvifilemod04/filemod.py
suvifilemod04-0.1.dist-info/METADATA
suvifilemod04-0.1.dist-info/WHEEL
suvifilemod04-0.1.dist-info/top_level.txt
suvifilemod04-0.1.dist-info/RECORD
