Metadata-Version: 2.1
Name: suvifilemod04
Version: 0.1
Summary: Basic file functions
Home-page: UNKNOWN
Author: suvansh
Author-email: suvanshgupta2004@gmail.com
License: UNKNOWN
Keywords: python
Platform: UNKNOWN
Classifier: Development Status :: 1 - Planning
Classifier: Intended Audience :: Developers
Classifier: Programming Language :: Python :: 3
Classifier: Operating System :: Unix
Classifier: Operating System :: MacOS :: MacOS X
Classifier: Operating System :: Microsoft :: Windows
